.gitignore
README.md
cloudbuild.yaml
pip_up_load_todo_list.txt
pyproject.toml
requirements.txt
requirements_test.txt
run_formatter_and_tests.py
setup.py
.github/FUNDING.yml
continuous_integration/36_pytest.dockerfile
continuous_integration/37_pytest.dockerfile
continuous_integration/38_pypy.dockerfile
continuous_integration/38_pytest.dockerfile
continuous_integration/38_pytest_ci.dockerfile
continuous_integration/CreateLinuxImages.dockerfile
continuous_integration/test_pip_install.dockerfile
images/histogram.png
images/pythondice_logo.png
images/pythondice_logo_128x128.png
images/pythondice_logo_32x32.png
images/pythondice_logo_48x48.png
images/pythondice_logo_512x512.png
images/pythondice_logo_512x512_background_1d3891.png
images/pythondice_logo_96x96.png
python_dice/__init__.py
python_dice.egg-info/PKG-INFO
python_dice.egg-info/SOURCES.txt
python_dice.egg-info/dependency_links.txt
python_dice.egg-info/requires.txt
python_dice.egg-info/top_level.txt
python_dice/interface/__init__.py
python_dice/interface/i_python_dice_interpreter.py
python_dice/interface/i_python_dice_lexer.py
python_dice/interface/i_python_dice_parser.py
python_dice/interface/constraint/__init__.py
python_dice/interface/constraint/i_constraint.py
python_dice/interface/constraint/i_constraint_factory.py
python_dice/interface/constraint/i_constraint_merger.py
python_dice/interface/constraint/i_constraint_set.py
python_dice/interface/constraint/i_constraint_set_factory.py
python_dice/interface/constraint/i_impossible_constraint.py
python_dice/interface/constraint/i_null_constraint.py
python_dice/interface/constraint/i_var_value_constraint.py
python_dice/interface/expression/__init__.py
python_dice/interface/expression/i_dice_expression.py
python_dice/interface/probability_distribution/__init__.py
python_dice/interface/probability_distribution/i_probability_distribution.py
python_dice/interface/probability_distribution/i_probability_distribution_factory.py
python_dice/interface/probability_distribution/i_probability_distribution_state.py
python_dice/interface/probability_distribution/i_probability_distribution_state_factory.py
