Metadata-Version: 2.1
Name: python-dice
Version: 2.0.2
Summary: a statistical dice library for python
Home-page: https://github.com/markbrockettrobson/python_dice
Author: Mark Brockett Robson
Author-email: mark.brockett.robson@gmail.com
License: UNKNOWN
Platform: UNKNOWN
Classifier: Programming Language :: Python :: 3
Classifier: License :: OSI Approved :: MIT License
Classifier: Operating System :: OS Independent
Requires-Python: >=3.6
